review/__init__.py
review/admin.py
review/apps.py
review/forms.py
review/models.py
review/tests.py
review/urls.py
review/views.py
review/migrations/0001_initial.py
review/migrations/__init__.py
review/templatetags/__init__.py
review/templatetags/django_review.py
django_product_review-0.0.2.dist-info/LICENSE
django_product_review-0.0.2.dist-info/METADATA
django_product_review-0.0.2.dist-info/WHEEL
django_product_review-0.0.2.dist-info/top_level.txt
django_product_review-0.0.2.dist-info/RECORD
